facelock/__init__.py
facelock/facial_recognition.py
facelock-0.1.2.dist-info/licenses/LICENSE
facelock-0.1.2.dist-info/METADATA
facelock-0.1.2.dist-info/WHEEL
facelock-0.1.2.dist-info/top_level.txt
facelock-0.1.2.dist-info/RECORD
